JES/__init__.py
siena_mls/__init__.py
siena_mls/animate_functions.py
siena_mls/image_functions.py
siena_mls/management_service.py
siena_mls/sound_functions.py
siena_mls-37.dist-info/METADATA
siena_mls-37.dist-info/WHEEL
siena_mls-37.dist-info/RECORD
