Metadata-Version: 2.4
Name: siena_mls
Version: 37
Summary: Multimedia Environment for Students
License: aGPLv3
Author: Robin Flatland
Author-email: flatland@siena.edu
Requires-Python: >=3.10,<3.14
Classifier: License :: Other/Proprietary License
Classifier: Programming Language :: Python :: 3
Classifier: Programming Language :: Python :: 3.10
Classifier: Programming Language :: Python :: 3.11
Classifier: Programming Language :: Python :: 3.12
Classifier: Programming Language :: Python :: 3.13
Requires-Dist: Pillow (>=10.2,<11.0)
Requires-Dist: matplotlib (>=3.8,<4.0)
Requires-Dist: nbformat (>=5.10.4,<6.0.0)
Requires-Dist: numpy (>=1.23.5,<2.3.0)
Requires-Dist: plotly (>=6.3.1,<7.0.0)
Requires-Dist: python-resize-image (>=1.1.20,<2.0.0)
Requires-Dist: scipy (>=1.14,<2.0)
Requires-Dist: sidecar (>=0.8.0,<0.9.0)
Project-URL: Bug Tracker, https://github.com/Introduction-To-CS-Siena-College/Siena-MLS-py/issues
Project-URL: Homepage, https://csis110.com/mls
Project-URL: Repository, https://github.com/Introduction-To-CS-Siena-College/Siena-MLS-py
